bindpyrame/__init__.py
bindpyrame/bindpyrame.py
bindpyrame/proxy.py
bindpyrame/sendcmd.py
bindpyrame-0.3.dist-info/LICENSE
bindpyrame-0.3.dist-info/METADATA
bindpyrame-0.3.dist-info/WHEEL
bindpyrame-0.3.dist-info/top_level.txt
bindpyrame-0.3.dist-info/RECORD
