Metadata-Version: 2.1
Name: bindpyrame
Version: 0.3
Summary: A module to bind to pyrame in pure python 3
Home-page: https://github.com/llr-online/bindpyrame/tree/master
Author: llr-online
Author-email: lorenzo.bernardi@llr.in2p3.fr
License: GPLv3
Platform: UNKNOWN
Classifier: Development Status :: 4 - Beta
Classifier: Programming Language :: Python :: 3
Classifier: License :: OSI Approved :: GNU General Public License v3 or later (GPLv3+)
Classifier: Operating System :: OS Independent
Requires-Python: >=3.0
